win_pyxs/__init__.py
win_pyxs/__main__.py
win_pyxs/exceptions.py
win_pyxs/gplpv.py
win_pyxs/winpv.py
win_pyxs-0.1.1.dist-info/LICENSE
win_pyxs-0.1.1.dist-info/METADATA
win_pyxs-0.1.1.dist-info/WHEEL
win_pyxs-0.1.1.dist-info/top_level.txt
win_pyxs-0.1.1.dist-info/zip-safe
win_pyxs-0.1.1.dist-info/RECORD
