Metadata-Version: 2.1
Name: win-pyxs
Version: 0.1.1
Summary: Windows compatibility for pyxs
Home-page: https://github.com/joelnb/win-pyxs
Author: Joel Noyce Barnham
Author-email: joelnbarnham@gmail.com
License: UNKNOWN
Keywords: pyxs xenstore xen
Platform: UNKNOWN
Classifier: Development Status :: 3 - Alpha
Classifier: Intended Audience :: Developers
Classifier: Natural Language :: English
Classifier: Operating System :: Microsoft :: Windows
Classifier: Programming Language :: Python
Classifier: Programming Language :: Python :: 2
Classifier: Programming Language :: Python :: 2.7
Classifier: Programming Language :: Python :: 3
Classifier: Programming Language :: Python :: 3.4
Classifier: Programming Language :: Python :: 3.5
Classifier: Programming Language :: Python :: 3.6
Classifier: Programming Language :: Python :: 3.7
Classifier: Programming Language :: Python :: 3.8
Requires-Dist: pywin32
Requires-Dist: pyxs
Requires-Dist: six
Requires-Dist: WMI
